.coveragerc
.pylintrc
.testr.conf
AUTHORS
CONTRIBUTING.rst
ChangeLog
HACKING.rst
LICENSE
MANIFEST.in
README.rst
babel.cfg
openstack-common.conf
requirements.txt
run_tests.sh
setup.cfg
setup.py
test-requirements.txt
tox.ini
devstack/local.conf.sample
devstack/plugin.sh
devstack/settings
doc/source/conf.py
doc/source/contributing.rst
doc/source/index.rst
doc/source/installation.rst
doc/source/readme.rst
doc/source/usage.rst
doc/source/specs/index.rst
doc/source/specs/skeleton.rst
etc/neutron/plugins/plumgrid/plumgrid.ini
networking_plumgrid/__init__.py
networking_plumgrid/_i18n.py
networking_plumgrid.egg-info/PKG-INFO
networking_plumgrid.egg-info/SOURCES.txt
networking_plumgrid.egg-info/dependency_links.txt
networking_plumgrid.egg-info/entry_points.txt
networking_plumgrid.egg-info/not-zip-safe
networking_plumgrid.egg-info/pbr.json
networking_plumgrid.egg-info/requires.txt
networking_plumgrid.egg-info/top_level.txt
networking_plumgrid/neutron/__init__.py
networking_plumgrid/neutron/plugins/README
networking_plumgrid/neutron/plugins/__init__.py
networking_plumgrid/neutron/plugins/plugin.py
networking_plumgrid/neutron/plugins/plugin_ver.py
networking_plumgrid/neutron/plugins/common/__init__.py
networking_plumgrid/neutron/plugins/common/constants.py
networking_plumgrid/neutron/plugins/common/exceptions.py
networking_plumgrid/neutron/plugins/common/l2_exceptions.py
networking_plumgrid/neutron/plugins/common/l2gw_validators.py
networking_plumgrid/neutron/plugins/common/pg_helper.py
networking_plumgrid/neutron/plugins/common/policy_exceptions.py
networking_plumgrid/neutron/plugins/common/policy_validators.py
networking_plumgrid/neutron/plugins/common/locking/__init__.py
networking_plumgrid/neutron/plugins/common/locking/lock.py
networking_plumgrid/neutron/plugins/common/locking/lock_object.py
networking_plumgrid/neutron/plugins/db/__init__.py
networking_plumgrid/neutron/plugins/db/api.py
networking_plumgrid/neutron/plugins/db/pg_models.py
networking_plumgrid/neutron/plugins/db/pgdb.py
networking_plumgrid/neutron/plugins/db/utils.py
networking_plumgrid/neutron/plugins/db/extlink/__init__.py
networking_plumgrid/neutron/plugins/db/extlink/ext_link_db.py
networking_plumgrid/neutron/plugins/db/l2gateway/__init__.py
networking_plumgrid/neutron/plugins/db/l2gateway/db_query.py
